tauros_api/__init__.py
tauros_api/exceptions.py
tauros_api/request.py
tauros_api/response.py
tests/__init__.py
tests/test_request_post.py
tauros_api-1.5.3.dist-info/LICENSE
tauros_api-1.5.3.dist-info/METADATA
tauros_api-1.5.3.dist-info/WHEEL
tauros_api-1.5.3.dist-info/top_level.txt
tauros_api-1.5.3.dist-info/RECORD
