Metadata-Version: 2.1
Name: tauros-api
Version: 1.5.3
Summary: This module is for connection with Tauros API.
Home-page: https://github.com/coinbtr/tauros-api-python
Author: Altcoins Mex S.A.P.I. de C.V.
Author-email: contacto@tauros.io
License: UNKNOWN
Platform: UNKNOWN
Classifier: Programming Language :: Python :: 3
Classifier: Programming Language :: Python :: 2.7
Classifier: License :: OSI Approved :: GNU General Public License v3 (GPLv3)
Classifier: Operating System :: OS Independent
Requires-Python: >=2.6, >=3.6
Requires-Dist: requests (<3,>=2.23.0)
